flake8_rst/__init__.py
flake8_rst/__main__.py
flake8_rst/application.py
flake8_rst/checker.py
flake8_rst/cli.py
flake8_rst/rst.py
flake8_rst/sourceblock.py
flake8_rst/sphinxext/__init__.py
flake8_rst/sphinxext/custom_roles.py
flake8_rst-0.8.0.dist-info/LICENSE
flake8_rst-0.8.0.dist-info/METADATA
flake8_rst-0.8.0.dist-info/WHEEL
flake8_rst-0.8.0.dist-info/entry_points.txt
flake8_rst-0.8.0.dist-info/top_level.txt
flake8_rst-0.8.0.dist-info/RECORD
