Metadata-Version: 2.1
Name: flake8-rst
Version: 0.8.0
Summary: flake8 for code in rst files and docstrings
Home-page: https://github.com/kataev/flake8-rst
Author: Denis Kataev
Author-email: denis.a.kataev@gmail.com
License: MIT
Platform: UNKNOWN
Classifier: Programming Language :: Python :: 3
Classifier: Programming Language :: Python :: 2
Classifier: License :: OSI Approved :: MIT License
Classifier: Operating System :: OS Independent
Requires-Dist: flake8 (>=3.5.0)
